sentimentx/__init__.py
sentimentx/deep_learning.py
sentimentx/emotions.py
sentimentx/lexicon.py
sentimentx/sentiment.py
sentimentx-0.0.4.dist-info/METADATA
sentimentx-0.0.4.dist-info/WHEEL
sentimentx-0.0.4.dist-info/top_level.txt
sentimentx-0.0.4.dist-info/RECORD
